onetracker_api/__init__.py
onetracker_api/__version__.py
onetracker_api/client.py
onetracker_api/exceptions.py
onetracker_api/models.py
onetracker_api/onetracker.py
onetracker_api-0.0.1.dist-info/LICENSE
onetracker_api-0.0.1.dist-info/METADATA
onetracker_api-0.0.1.dist-info/WHEEL
onetracker_api-0.0.1.dist-info/top_level.txt
onetracker_api-0.0.1.dist-info/RECORD
