Metadata-Version: 2.1
Name: onetracker-api
Version: 0.0.1
Summary: Asynchronous Python client for OneTracker.
Home-page: https://github.com/JeffResc/OneTracker-API
Author: JeffResc
Author-email: jeff@jeffresc.dev
License: GPLv3.0
Keywords: onetracker,api,async,client
Platform: UNKNOWN
Classifier: Framework :: AsyncIO
Classifier: Intended Audience :: Developers
Classifier: License :: OSI Approved :: GNU General Public License v3 (GPLv3)
Classifier: Natural Language :: English
Classifier: Programming Language :: Python :: 3.7
Classifier: Programming Language :: Python :: 3.8
Classifier: Programming Language :: Python :: 3
Classifier: Topic :: Software Development :: Libraries :: Python Modules
License-File: LICENSE
Requires-Dist: aiohttp (==3.8.1)
